achilles/__init__.py
achilles/achilles.py
achilles/cli.py
achilles/data_models.py
achilles/printers.py
achilles/profiling.py
achilles/prompts.py
achilles/run_achilles.py
achilles/strategies.py
achilles/agents/__init__.py
achilles/agents/analysis_agent.py
achilles/agents/cpp_agent.py
achilles/file_ops/__init__.py
achilles/file_ops/function_ops.py
achilles_optimizer-0.2.0.dist-info/METADATA
achilles_optimizer-0.2.0.dist-info/WHEEL
achilles_optimizer-0.2.0.dist-info/entry_points.txt
achilles_optimizer-0.2.0.dist-info/top_level.txt
achilles_optimizer-0.2.0.dist-info/RECORD
