Metadata-Version: 2.4
Name: achilles-optimizer
Version: 0.2.0
Summary: Claude-Powered Python Performance Optimizer
Requires-Python: >=3.13
Requires-Dist: anthropic>=0.50.0
Requires-Dist: build>=1.2.2.post1
Requires-Dist: dotenv>=0.9.9
Requires-Dist: pybind11>=2.13.6
Requires-Dist: rich>=14.0.0
Requires-Dist: setuptools>=79.0.1
Requires-Dist: twine>=6.1.0
